temaanalyzer/__init__.py
temaanalyzer/temafunctions.py
temaanalyzer/interactive/TEMAExampleFile.txt
temaanalyzer/interactive/goodExport.csv
temaanalyzer/interactive/temaanalyzer-notebook.ipynb
tema_analyzer-1.4.1.dist-info/LICENSE.txt
tema_analyzer-1.4.1.dist-info/METADATA
tema_analyzer-1.4.1.dist-info/WHEEL
tema_analyzer-1.4.1.dist-info/top_level.txt
tema_analyzer-1.4.1.dist-info/RECORD
