Metadata-Version: 2.1
Name: tema-analyzer
Version: 1.4.1
Summary: Analysis and processing of TEMA data files
Home-page: https://github.com/lviornery/tema-analyzer
Author: Luis Viornery & Taryn Imamura
Author-email: lviornery@cmu.edu
License: MIT
License-File: LICENSE.txt
Requires-Dist: pandas (>=1.3)
Provides-Extra: interactive
Requires-Dist: jupyterlab ; extra == 'interactive'
Requires-Dist: altair ; extra == 'interactive'
